mcp_server_code_assist/__init__.py
mcp_server_code_assist/__main__.py
mcp_server_code_assist/base_tools.py
mcp_server_code_assist/server.py
mcp_server_code_assist/xml_parser.py
mcp_server_code_assist/prompts/__init__.py
mcp_server_code_assist/prompts/git_prompt.py
mcp_server_code_assist/prompts/prompt_manager.py
mcp_server_code_assist/tools/__init__.py
mcp_server_code_assist/tools/dir_tools.py
mcp_server_code_assist/tools/file_tools.py
mcp_server_code_assist/tools/git_tools.py
mcp_server_code_assist/tools/invoke.py
mcp_server_code_assist/tools/models.py
mcp_server_code_assist/tools/tools_manager.py
mseep_mcp_server_code_assist-0.2.4.dist-info/METADATA
mseep_mcp_server_code_assist-0.2.4.dist-info/WHEEL
mseep_mcp_server_code_assist-0.2.4.dist-info/entry_points.txt
mseep_mcp_server_code_assist-0.2.4.dist-info/top_level.txt
mseep_mcp_server_code_assist-0.2.4.dist-info/RECORD
